{
  "generated_at": "2026-05-28T06:59:52+00:00",
  "variant": "enhanced",
  "total_documents": 1000,
  "field_extraction_rates": {
    "platforms": {
      "count": 245,
      "rate": 0.245
    },
    "languages": {
      "count": 440,
      "rate": 0.44
    },
    "action_types": {
      "count": 872,
      "rate": 0.872
    },
    "target_domains": {
      "count": 927,
      "rate": 0.927
    },
    "output_formats": {
      "count": 472,
      "rate": 0.472
    },
    "metrics": {
      "count": 137,
      "rate": 0.137
    }
  },
  "top_values_per_field": {
    "platforms": [
      [
        "github",
        80
      ],
      [
        "google",
        59
      ],
      [
        "docker",
        26
      ],
      [
        "azure",
        22
      ],
      [
        "youtube",
        21
      ],
      [
        "kubernetes",
        18
      ],
      [
        "slack",
        16
      ],
      [
        "tmall",
        11
      ],
      [
        "aws",
        11
      ],
      [
        "tiktok",
        10
      ],
      [
        "instagram",
        9
      ],
      [
        "facebook",
        8
      ],
      [
        "reddit",
        7
      ],
      [
        "linkedin",
        6
      ],
      [
        "twitter",
        6
      ]
    ],
    "action_types": [
      [
        "create",
        235
      ],
      [
        "generate",
        189
      ],
      [
        "analyze",
        177
      ],
      [
        "validate",
        166
      ],
      [
        "design",
        146
      ],
      [
        "optimize",
        133
      ],
      [
        "review",
        114
      ],
      [
        "automate",
        112
      ],
      [
        "build",
        108
      ],
      [
        "test",
        97
      ],
      [
        "search",
        96
      ],
      [
        "extract",
        89
      ],
      [
        "detect",
        76
      ],
      [
        "monitor",
        54
      ],
      [
        "verify",
        42
      ]
    ],
    "target_domains": [
      [
        "frontend",
        838
      ],
      [
        "api",
        195
      ],
      [
        "design",
        141
      ],
      [
        "content",
        131
      ],
      [
        "ai",
        126
      ],
      [
        "security",
        107
      ],
      [
        "ui",
        78
      ],
      [
        "image",
        57
      ],
      [
        "marketing",
        44
      ],
      [
        "backend",
        34
      ],
      [
        "ios",
        32
      ],
      [
        "accessibility",
        31
      ],
      [
        "infrastructure",
        31
      ],
      [
        "video",
        30
      ],
      [
        "mobile",
        28
      ]
    ],
    "metrics": [
      [
        "3 step",
        6
      ],
      [
        "2 step",
        5
      ],
      [
        "3 test",
        4
      ],
      [
        "4 step",
        4
      ],
      [
        "5 step",
        4
      ],
      [
        "4 level",
        4
      ],
      [
        "1 rule",
        4
      ],
      [
        "6 categories",
        3
      ],
      [
        "3 level",
        3
      ],
      [
        "1 step",
        3
      ],
      [
        "6 rule",
        3
      ],
      [
        "3 item",
        3
      ],
      [
        "3 layer",
        3
      ],
      [
        "2 test",
        3
      ],
      [
        "7 item",
        2
      ]
    ],
    "languages": [
      [
        "python",
        83
      ],
      [
        "react",
        80
      ],
      [
        "typescript",
        58
      ],
      [
        "javascript",
        58
      ],
      [
        "html",
        53
      ],
      [
        "go",
        45
      ],
      [
        "node.js",
        41
      ],
      [
        "next.js",
        39
      ],
      [
        "css",
        37
      ],
      [
        "sql",
        28
      ],
      [
        "vue",
        28
      ],
      [
        "docker",
        26
      ],
      [
        "swift",
        26
      ],
      [
        "postgresql",
        24
      ],
      [
        "express",
        19
      ]
    ],
    "output_formats": [
      [
        "api",
        195
      ],
      [
        "json",
        152
      ],
      [
        "markdown",
        73
      ],
      [
        "html",
        53
      ],
      [
        "rest",
        38
      ],
      [
        "pdf",
        30
      ],
      [
        "sql",
        28
      ],
      [
        "yaml",
        24
      ],
      [
        "csv",
        21
      ],
      [
        "xml",
        17
      ],
      [
        "graphql",
        16
      ],
      [
        "png",
        15
      ],
      [
        "webhook",
        12
      ],
      [
        "docx",
        11
      ],
      [
        "toml",
        9
      ]
    ]
  },
  "info_point_distribution": {
    "0": 9,
    "1": 61,
    "2": 246,
    "3": 313,
    "4": 269,
    "5": 87,
    "6": 15
  },
  "documents_with_all_fields": 102,
  "documents_with_no_extraction": 9,
  "total_evidence_items": 17733,
  "explainability": {
    "total_documents": 1000,
    "field_summary": {
      "platforms": {
        "documents_with_evidence": 748,
        "coverage_rate": 0.748,
        "evidence_items": 3501,
        "evidence_per_document": 4.6805,
        "top_sources": [
          {
            "source": "gliner_unknown",
            "count": 2310
          },
          {
            "source": "keyword_fallback",
            "count": 760
          },
          {
            "source": "gliner_direct",
            "count": 274
          },
          {
            "source": "gliner_normalized",
            "count": 157
          }
        ],
        "samples": [
          {
            "skill_name": "maishou",
            "skill_id": "cb39f4944827",
            "field": "platforms",
            "value": "taobao",
            "rule_source": "gliner_direct",
            "pattern_source": "platform or tool",
            "matched_text": "Taobao",
            "context": "...e-commerce platforms. Supports eight platforms: Taobao, Tmall, JD.com, PinDuoDuo, Suning, VIP.com, Kao..."
          },
          {
            "skill_name": "entity-optimizer",
            "skill_id": "288ba3b4b296",
            "field": "platforms",
            "value": "Knowledge Graph",
            "rule_source": "gliner_unknown",
            "pattern_source": "platform or tool",
            "matched_text": "Knowledge Graph",
            "context": "...ystems. Evaluates entity presence across Google Knowledge Graph, Wikidata, Wikipedia, and AI systems with a 47-..."
          }
        ]
      },
      "languages": {
        "documents_with_evidence": 778,
        "coverage_rate": 0.778,
        "evidence_items": 4059,
        "evidence_per_document": 5.2172,
        "top_sources": [
          {
            "source": "gliner_unknown",
            "count": 1639
          },
          {
            "source": "keyword_fallback",
            "count": 1440
          },
          {
            "source": "gliner_direct",
            "count": 737
          },
          {
            "source": "gliner_normalized",
            "count": 243
          }
        ],
        "samples": [
          {
            "skill_name": "schema-markup-generator",
            "skill_id": "7cffdee4895f",
            "field": "languages",
            "value": "html",
            "rule_source": "keyword_fallback",
            "pattern_source": "\\bhtml\\b",
            "matched_text": "HTML",
            "context": "...RP preview mockups, implementation guidance for HTML placement, and validation checkpoints for synta..."
          },
          {
            "skill_name": "actionbook",
            "skill_id": "8cc18095a46f",
            "field": "languages",
            "value": "Unix",
            "rule_source": "gliner_unknown",
            "pattern_source": "programming language or framework",
            "matched_text": "Unix",
            "context": "...ation manually in the same session Daemon mode (Unix/CDP) maintains a persistent WebSocket connectio..."
          }
        ]
      },
      "action_types": {
        "documents_with_evidence": 889,
        "coverage_rate": 0.889,
        "evidence_items": 4318,
        "evidence_per_document": 4.8571,
        "top_sources": [
          {
            "source": "alias_fallback",
            "count": 1900
          },
          {
            "source": "keyword_fallback",
            "count": 1837
          },
          {
            "source": "gliner_unknown",
            "count": 512
          },
          {
            "source": "gliner_normalized",
            "count": 68
          },
          {
            "source": "gliner_direct",
            "count": 1
          }
        ],
        "samples": [
          {
            "skill_name": "maishou",
            "skill_id": "cb39f4944827",
            "field": "action_types",
            "value": "search",
            "rule_source": "keyword_fallback",
            "pattern_source": "\\bsearch\\b",
            "matched_text": "Search",
            "context": "...ing, VIP.com, Kaola, Douyin, Kuaishou, and 1688 Search products by keyword with pagination support acr..."
          },
          {
            "skill_name": "domain-authority-auditor",
            "skill_id": "bcbc9af8782d",
            "field": "action_types",
            "value": "audit",
            "rule_source": "keyword_fallback",
            "pattern_source": "\\baudit\\b",
            "matched_text": "audit",
            "context": "...uditor marketing Comprehensive domain authority audit across 40 standardized criteria with weighted s..."
          }
        ]
      },
      "target_domains": {
        "documents_with_evidence": 927,
        "coverage_rate": 0.927,
        "evidence_items": 3090,
        "evidence_per_document": 3.3333,
        "top_sources": [
          {
            "source": "keyword_fallback",
            "count": 3067
          },
          {
            "source": "gliner_unknown",
            "count": 16
          },
          {
            "source": "gliner_direct",
            "count": 6
          },
          {
            "source": "gliner_normalized",
            "count": 1
          }
        ],
        "samples": [
          {
            "skill_name": "maishou",
            "skill_id": "cb39f4944827",
            "field": "target_domains",
            "value": "e-commerce",
            "rule_source": "keyword_fallback",
            "pattern_source": "\\be\\-commerce\\b",
            "matched_text": "e-commerce",
            "context": "...product prices and coupons across major Chinese e-commerce platforms. Supports eight platforms: Taobao, Tm..."
          },
          {
            "skill_name": "domain-authority-auditor",
            "skill_id": "bcbc9af8782d",
            "field": "target_domains",
            "value": "SaaS",
            "rule_source": "gliner_unknown",
            "pattern_source": "target domain or industry",
            "matched_text": "SaaS",
            "context": "...by domain type (Content Publisher, E-commerce, SaaS, etc.) Detects critical manipulation red flags..."
          }
        ]
      },
      "output_formats": {
        "documents_with_evidence": 565,
        "coverage_rate": 0.565,
        "evidence_items": 2216,
        "evidence_per_document": 3.9221,
        "top_sources": [
          {
            "source": "keyword_fallback",
            "count": 1258
          },
          {
            "source": "gliner_unknown",
            "count": 585
          },
          {
            "source": "gliner_direct",
            "count": 260
          },
          {
            "source": "gliner_normalized",
            "count": 113
          }
        ],
        "samples": [
          {
            "skill_name": "schema-markup-generator",
            "skill_id": "7cffdee4895f",
            "field": "output_formats",
            "value": "ISO 8601",
            "rule_source": "gliner_unknown",
            "pattern_source": "output format or file type",
            "matched_text": "ISO 8601",
            "context": "...red and optional properties, absolute URLs, and ISO 8601 date formatting Includes SERP preview mockups,..."
          },
          {
            "skill_name": "manim-composer",
            "skill_id": "9b692834fd7f",
            "field": "output_formats",
            "value": "md file",
            "rule_source": "gliner_unknown",
            "pattern_source": "output format or file type",
            "matched_text": "md file",
            "context": "...pe the narrative Outputs a comprehensive scenes.md file specifying each scene's purpose, visual element..."
          }
        ]
      },
      "metrics": {
        "documents_with_evidence": 258,
        "coverage_rate": 0.258,
        "evidence_items": 549,
        "evidence_per_document": 2.1279,
        "top_sources": [
          {
            "source": "gliner_direct",
            "count": 346
          },
          {
            "source": "metric_regex",
            "count": 203
          }
        ],
        "samples": [
          {
            "skill_name": "domain-authority-auditor",
            "skill_id": "bcbc9af8782d",
            "field": "metrics",
            "value": "Citation",
            "rule_source": "gliner_direct",
            "pattern_source": "quantitative metric",
            "matched_text": "Citation",
            "context": "...in type. Evaluates domains across 4 dimensions (Citation, Identity, Trust, Eminence) with per-item Pass/..."
          },
          {
            "skill_name": "entity-optimizer",
            "skill_id": "288ba3b4b296",
            "field": "metrics",
            "value": "6",
            "rule_source": "metric_regex",
            "pattern_source": "(\\d+)[\\-\\s]*(signal|criteria|item|point|step|dimension|layer|level|module|metric|check|rule|test|factor)",
            "matched_text": "6 signal",
            "context": "6 signal"
          }
        ]
      }
    },
    "global_source_distribution": [
      {
        "source": "keyword_fallback",
        "count": 8362
      },
      {
        "source": "gliner_unknown",
        "count": 5062
      },
      {
        "source": "alias_fallback",
        "count": 1900
      },
      {
        "source": "gliner_direct",
        "count": 1624
      },
      {
        "source": "gliner_normalized",
        "count": 582
      },
      {
        "source": "metric_regex",
        "count": 203
      }
    ]
  }
}